django_image_uploader_widget-1.1.0.dist-info/licenses/LICENSE
image_uploader_widget/__init__.py
image_uploader_widget/admin.py
image_uploader_widget/widgets.py
image_uploader_widget/locale/es/LC_MESSAGES/django.mo
image_uploader_widget/locale/es/LC_MESSAGES/django.po
image_uploader_widget/locale/pt_BR/LC_MESSAGES/django.mo
image_uploader_widget/locale/pt_BR/LC_MESSAGES/django.po
image_uploader_widget/locale/ru/LC_MESSAGES/django.mo
image_uploader_widget/locale/ru/LC_MESSAGES/django.po
image_uploader_widget/postgres/__init__.py
image_uploader_widget/postgres/fields.py
image_uploader_widget/postgres/forms.py
image_uploader_widget/postgres/widget.py
image_uploader_widget/static/image_uploader_widget/css/image-uploader-inline.css
image_uploader_widget/static/image_uploader_widget/css/image-uploader-widget.css
image_uploader_widget/static/image_uploader_widget/js/image-uploader-inline.js
image_uploader_widget/static/image_uploader_widget/js/image-uploader-modal.js
image_uploader_widget/static/image_uploader_widget/js/image-uploader-widget.js
image_uploader_widget/static/image_uploader_widget/js/vendor/sortable.min.js
image_uploader_widget/templates/image_uploader_widget/admin/inline_image_uploader.html
image_uploader_widget/templates/image_uploader_widget/admin/inline_image_uploader_preview.html
image_uploader_widget/templates/image_uploader_widget/admin/inline_image_uploader_preview_widget.html
image_uploader_widget/templates/image_uploader_widget/admin/ordered_inline_image_uploader.html
image_uploader_widget/templates/image_uploader_widget/parts/preview.html
image_uploader_widget/templates/image_uploader_widget/postgres/image_array.html
image_uploader_widget/templates/image_uploader_widget/postgres/image_array_preview.html
image_uploader_widget/templates/image_uploader_widget/widget/image_uploader_widget.html
image_uploader_widget/templates/image_uploader_widget/widget/image_uploader_widget_preview.html
django_image_uploader_widget-1.1.0.dist-info/METADATA
django_image_uploader_widget-1.1.0.dist-info/WHEEL
django_image_uploader_widget-1.1.0.dist-info/top_level.txt
django_image_uploader_widget-1.1.0.dist-info/RECORD
