Metadata-Version: 2.4
Name: django-image-uploader-widget
Version: 1.1.0
Summary: Simple Image Uploader Widget for Django-Admin
Author-email: Eduardo Oliveira <eduardo_y05@outlook.com>
Maintainer-email: Eduardo Oliveira <eduardo_y05@outlook.com>
License: MIT License
Project-URL: homepage, https://github.com/inventare/django-image-uploader-widget
Project-URL: documentation, https://inventare.github.io/django-image-uploader-widget/
Keywords: django,admin,widget,image,uploader
Classifier: Development Status :: 5 - Production/Stable
Classifier: Environment :: Web Environment
Classifier: Framework :: Django
Classifier: Intended Audience :: Developers
Classifier: License :: OSI Approved :: MIT License
Classifier: Operating System :: OS Independent
Classifier: Programming Language :: Python
Classifier: Programming Language :: Python :: 3
Classifier: Programming Language :: Python :: 3.8
Classifier: Programming Language :: Python :: 3.9
Classifier: Programming Language :: Python :: 3.10
Classifier: Programming Language :: Python :: 3.11
Classifier: Programming Language :: Python :: 3.12
Requires-Python: >=3.8
License-File: LICENSE
Requires-Dist: django>=4.2
Requires-Dist: Pillow
Provides-Extra: dev
Requires-Dist: black; extra == "dev"
Requires-Dist: isort; extra == "dev"
Requires-Dist: pre-commit; extra == "dev"
Requires-Dist: poethepoet; extra == "dev"
Provides-Extra: test
Requires-Dist: playwright==1.48.0; extra == "test"
Provides-Extra: docs
Requires-Dist: mkdocs; extra == "docs"
Requires-Dist: mkdocs-material; extra == "docs"
Requires-Dist: mkdocs-glightbox; extra == "docs"
Requires-Dist: mkdocs-awesome-pages-plugin; extra == "docs"
Dynamic: license-file
